{"topics": {"justice": {"verses": [{"book": "Genesis", "chapter": 18, "verse": 19, "word": {"hebrewmodern": "\u05db\u05d9 \u05d9\u05d3\u05e2\u05ea\u05d9\u05d5 \u05dc\u05de\u05e2\u05df \u05d0\u05e9\u05e8 \u05d9\u05e6\u05d5\u05d4 \u05d0\u05ea \u05d1\u05e0\u05d9\u05d5 \u05d5\u05d0\u05ea \u05d1\u05d9\u05ea\u05d5 \u05d0\u05d7\u05e8\u05d9\u05d5 \u05d5\u05e9\u05de\u05e8\u05d5 \u05d3\u05e8\u05da \u05d9\u05d4\u05d5\u05d4 \u05dc\u05e2\u05e9\u05d5\u05ea \u05e6\u05d3\u05e7\u05d4 \u05d5\u05de\u05e9\u05e4\u05d8 \u05dc\u05de\u05e2\u05df \u05d4\u05d1\u05d9\u05d0 \u05d9\u05d4\u05d5\u05d4 \u05e2\u05dc \u05d0\u05d1\u05e8\u05d4\u05dd \u05d0\u05ea \u05d0\u05e9\u05e8 \u05d3\u05d1\u05e8 \u05e2\u05dc\u05d9\u05d5\u05c3\r\n"}}, {"book": "Deuteronomy", "chapter": 33, "verse": 21, "word": {"hebrewmodern": "\u05d5\u05d9\u05e8\u05d0 \u05e8\u05d0\u05e9\u05d9\u05ea \u05dc\u05d5 \u05db\u05d9 \u05e9\u05dd \u05d7\u05dc\u05e7\u05ea \u05de\u05d7\u05e7\u05e7 \u05e1\u05e4\u05d5\u05df \u05d5\u05d9\u05ea\u05d0 \u05e8\u05d0\u05e9\u05d9 \u05e2\u05dd \u05e6\u05d3\u05e7\u05ea \u05d9\u05d4\u05d5\u05d4 \u05e2\u05e9\u05d4 \u05d5\u05de\u05e9\u05e4\u05d8\u05d9\u05d5 \u05e2\u05dd \u05d9\u05e9\u05e8\u05d0\u05dc\u05c3\r\n"}}, {"book": "2 Samuel", "chapter": 8, "verse": 15, "word": {"hebrewmodern": "\u05d5\u05d9\u05de\u05dc\u05da \u05d3\u05d5\u05d3 \u05e2\u05dc \u05db\u05dc \u05d9\u05e9\u05e8\u05d0\u05dc \u05d5\u05d9\u05d4\u05d9 \u05d3\u05d5\u05d3 \u05e2\u05e9\u05d4 \u05de\u05e9\u05e4\u05d8 \u05d5\u05e6\u05d3\u05e7\u05d4 \u05dc\u05db\u05dc \u05e2\u05de\u05d5\u05c3\r\n"}}, {"book": "2 Samuel", "chapter": 15, "verse": 4, "word": {"hebrewmodern": "\u05d5\u05d9\u05d0\u05de\u05e8 \u05d0\u05d1\u05e9\u05dc\u05d5\u05dd \u05de\u05d9 \u05d9\u05e9\u05de\u05e0\u05d9 \u05e9\u05e4\u05d8 \u05d1\u05d0\u05e8\u05e5 \u05d5\u05e2\u05dc\u05d9 \u05d9\u05d1\u05d5\u05d0 \u05db\u05dc \u05d0\u05d9\u05e9 \u05d0\u05e9\u05e8 \u05d9\u05d4\u05d9\u05d4 \u05dc\u05d5 \u05e8\u05d9\u05d1 \u05d5\u05de\u05e9\u05e4\u05d8 \u05d5\u05d4\u05e6\u05d3\u05e7\u05ea\u05d9\u05d5\u05c3\r\n"}}, {"book": "1 Kings", "chapter": 10, "verse": 9, "word": {"hebrewmodern": "\u05d9\u05d4\u05d9 \u05d9\u05d4\u05d5\u05d4 \u05d0\u05dc\u05d4\u05d9\u05da \u05d1\u05e8\u05d5\u05da \u05d0\u05e9\u05e8 \u05d7\u05e4\u05e5 \u05d1\u05da \u05dc\u05ea\u05ea\u05da \u05e2\u05dc \u05db\u05e1\u05d0 \u05d9\u05e9\u05e8\u05d0\u05dc \u05d1\u05d0\u05d4\u05d1\u05ea \u05d9\u05d4\u05d5\u05d4 \u05d0\u05ea \u05d9\u05e9\u05e8\u05d0\u05dc \u05dc\u05e2\u05dc\u05dd \u05d5\u05d9\u05e9\u05d9\u05de\u05da \u05dc\u05de\u05dc\u05da \u05dc\u05e2\u05e9\u05d5\u05ea \u05de\u05e9\u05e4\u05d8 \u05d5\u05e6\u05d3\u05e7\u05d4\u05c3\r\n"}}, {"book": "1 Chronicles", "chapter": 18, "verse": 14, "word": {"hebrewmodern": "\u05d5\u05d9\u05de\u05dc\u05da \u05d3\u05d5\u05d9\u05d3 \u05e2\u05dc \u05db\u05dc \u05d9\u05e9\u05e8\u05d0\u05dc \u05d5\u05d9\u05d4\u05d9 \u05e2\u05e9\u05d4 \u05de\u05e9\u05e4\u05d8 \u05d5\u05e6\u05d3\u05e7\u05d4 \u05dc\u05db\u05dc \u05e2\u05de\u05d5\u05c3\r\n"}}, {"book": "2 Chronicles", "chapter": 9, "verse": 8, "word": {"hebrewmodern": "\u05d9\u05d4\u05d9 \u05d9\u05d4\u05d5\u05d4 \u05d0\u05dc\u05d4\u05d9\u05da \u05d1\u05e8\u05d5\u05da \u05d0\u05e9\u05e8 \u05d7\u05e4\u05e5 \u05d1\u05da \u05dc\u05ea\u05ea\u05da \u05e2\u05dc \u05db\u05e1\u05d0\u05d5 \u05dc\u05de\u05dc\u05da \u05dc\u05d9\u05d4\u05d5\u05d4 \u05d0\u05dc\u05d4\u05d9\u05da \u05d1\u05d0\u05d4\u05d1\u05ea \u05d0\u05dc\u05d4\u05d9\u05da \u05d0\u05ea \u05d9\u05e9\u05e8\u05d0\u05dc \u05dc\u05d4\u05e2\u05de\u05d9\u05d3\u05d5 \u05dc\u05e2\u05d5\u05dc\u05dd \u05d5\u05d9\u05ea\u05e0\u05da \u05e2\u05dc\u05d9\u05d4\u05dd \u05dc\u05de\u05dc\u05da \u05dc\u05e2\u05e9\u05d5\u05ea \u05de\u05e9\u05e4\u05d8 \u05d5\u05e6\u05d3\u05e7\u05d4\u05c3\r\n"}}, {"book": "Job", "chapter": 8, "verse": 3, "word": {"hebrewmodern": "\u05d4\u05d0\u05dc \u05d9\u05e2\u05d5\u05ea \u05de\u05e9\u05e4\u05d8 \u05d5\u05d0\u05dd \u05e9\u05d3\u05d9 \u05d9\u05e2\u05d5\u05ea \u05e6\u05d3\u05e7\u05c3\r\n"}}, {"book": "Job", "chapter": 16, "verse": 17, "word": {"hebrewmodern": "\u05e2\u05dc \u05dc\u05d0 \u05d7\u05de\u05e1 \u05d1\u05db\u05e4\u05d9 \u05d5\u05ea\u05e4\u05dc\u05ea\u05d9 \u05d6\u05db\u05d4\u05c3\r\n"}}, {"book": "Job", "chapter": 36, "verse": 17, "word": {"hebrewmodern": "\u05d5\u05d3\u05d9\u05df \u05e8\u05e9\u05e2 \u05de\u05dc\u05d0\u05ea \u05d3\u05d9\u05df \u05d5\u05de\u05e9\u05e4\u05d8 \u05d9\u05ea\u05de\u05db\u05d5\u05c3\r\n"}}, {"book": "Job", "chapter": 37, "verse": 23, "word": {"hebrewmodern": "\u05e9\u05d3\u05d9 \u05dc\u05d0 \u05de\u05e6\u05d0\u05e0\u05d4\u05d5 \u05e9\u05d2\u05d9\u05d0 \u05db\u05d7 \u05d5\u05de\u05e9\u05e4\u05d8 \u05d5\u05e8\u05d1 \u05e6\u05d3\u05e7\u05d4 \u05dc\u05d0 \u05d9\u05e2\u05e0\u05d4\u05c3\r\n"}}, {"book": "Psalms", "chapter": 82, "verse": 3, "word": {"hebrewmodern": "\u05e9\u05e4\u05d8\u05d5 \u05d3\u05dc \u05d5\u05d9\u05ea\u05d5\u05dd \u05e2\u05e0\u05d9 \u05d5\u05e8\u05e9 \u05d4\u05e6\u05d3\u05d9\u05e7\u05d5\u05c3\r\n"}}, {"book": "Psalms", "chapter": 119, "verse": 121, "word": {"hebrewmodern": "\u05e2\u05e9\u05d9\u05ea\u05d9 \u05de\u05e9\u05e4\u05d8 \u05d5\u05e6\u05d3\u05e7 \u05d1\u05dc \u05ea\u05e0\u05d9\u05d7\u05e0\u05d9 \u05dc\u05e2\u05e9\u05e7\u05d9\u05c3\r\n"}}, {"book": "Proverbs", "chapter": 1, "verse": 3, "word": {"hebrewmodern": "\u05dc\u05e7\u05d7\u05ea \u05de\u05d5\u05e1\u05e8 \u05d4\u05e9\u05db\u05dc \u05e6\u05d3\u05e7 \u05d5\u05de\u05e9\u05e4\u05d8 \u05d5\u05de\u05d9\u05e9\u05e8\u05d9\u05dd\u05c3\r\n"}}, {"book": "Proverbs", "chapter": 8, "verse": 15, "word": {"hebrewmodern": "\u05d1\u05d9 \u05de\u05dc\u05db\u05d9\u05dd \u05d9\u05de\u05dc\u05db\u05d5 \u05d5\u05e8\u05d5\u05d6\u05e0\u05d9\u05dd \u05d9\u05d7\u05e7\u05e7\u05d5 \u05e6\u05d3\u05e7\u05c3\r\n"}}, {"book": "Proverbs", "chapter": 21, "verse": 3, "word": {"hebrewmodern": "\u05e2\u05e9\u05d4 \u05e6\u05d3\u05e7\u05d4 \u05d5\u05de\u05e9\u05e4\u05d8 \u05e0\u05d1\u05d7\u05e8 \u05dc\u05d9\u05d4\u05d5\u05d4 \u05de\u05d6\u05d1\u05d7\u05c3\r\n"}}, {"book": "Ecclesiastes", "chapter": 5, "verse": 8, "word": {"hebrewmodern": "\u05d0\u05dd \u05e2\u05e9\u05e7 \u05e8\u05e9 \u05d5\u05d2\u05d6\u05dc \u05de\u05e9\u05e4\u05d8 \u05d5\u05e6\u05d3\u05e7 \u05ea\u05e8\u05d0\u05d4 \u05d1\u05de\u05d3\u05d9\u05e0\u05d4 \u05d0\u05dc \u05ea\u05ea\u05de\u05d4 \u05e2\u05dc \u05d4\u05d7\u05e4\u05e5 \u05db\u05d9 \u05d2\u05d1\u05d4 \u05de\u05e2\u05dc \u05d2\u05d1\u05d4 \u05e9\u05de\u05e8 \u05d5\u05d2\u05d1\u05d4\u05d9\u05dd \u05e2\u05dc\u05d9\u05d4\u05dd\u05c3\r\n"}}, {"book": "Isaiah", "chapter": 9, "verse": 7, "word": {"hebrewmodern": "\u05dc\u05de\u05e8\u05d1\u05d4 \u05d4\u05de\u05e9\u05e8\u05d4 \u05d5\u05dc\u05e9\u05dc\u05d5\u05dd \u05d0\u05d9\u05df \u05e7\u05e5 \u05e2\u05dc \u05db\u05e1\u05d0 \u05d3\u05d5\u05d3 \u05d5\u05e2\u05dc \u05de\u05de\u05dc\u05db\u05ea\u05d5 \u05dc\u05d4\u05db\u05d9\u05df \u05d0\u05ea\u05d4 \u05d5\u05dc\u05e1\u05e2\u05d3\u05d4 \u05d1\u05de\u05e9\u05e4\u05d8 \u05d5\u05d1\u05e6\u05d3\u05e7\u05d4 \u05de\u05e2\u05ea\u05d4 \u05d5\u05e2\u05d3 \u05e2\u05d5\u05dc\u05dd \u05e7\u05e0\u05d0\u05ea \u05d9\u05d4\u05d5\u05d4 \u05e6\u05d1\u05d0\u05d5\u05ea \u05ea\u05e2\u05e9\u05d4 \u05d6\u05d0\u05ea\u05c3\r\n"}}, {"book": "Isaiah", "chapter": 56, "verse": 1, "word": {"hebrewmodern": "\u05db\u05d4 \u05d0\u05de\u05e8 \u05d9\u05d4\u05d5\u05d4 \u05e9\u05de\u05e8\u05d5 \u05de\u05e9\u05e4\u05d8 \u05d5\u05e2\u05e9\u05d5 \u05e6\u05d3\u05e7\u05d4 \u05db\u05d9 \u05e7\u05e8\u05d5\u05d1\u05d4 \u05d9\u05e9\u05d5\u05e2\u05ea\u05d9 \u05dc\u05d1\u05d5\u05d0 \u05d5\u05e6\u05d3\u05e7\u05ea\u05d9 \u05dc\u05d4\u05d2\u05dc\u05d5\u05ea\u05c3\r\n"}}, {"book": "Isaiah", "chapter": 58, "verse": 2, "word": {"hebrewmodern": "\u05d5\u05d0\u05d5\u05ea\u05d9 \u05d9\u05d5\u05dd \u05d9\u05d5\u05dd \u05d9\u05d3\u05e8\u05e9\u05d5\u05df \u05d5\u05d3\u05e2\u05ea \u05d3\u05e8\u05db\u05d9 \u05d9\u05d7\u05e4\u05e6\u05d5\u05df \u05db\u05d2\u05d5\u05d9 \u05d0\u05e9\u05e8 \u05e6\u05d3\u05e7\u05d4 \u05e2\u05e9\u05d4 \u05d5\u05de\u05e9\u05e4\u05d8 \u05d0\u05dc\u05d4\u05d9\u05d5 \u05dc\u05d0 \u05e2\u05d6\u05d1 \u05d9\u05e9\u05d0\u05dc\u05d5\u05e0\u05d9 \u05de\u05e9\u05e4\u05d8\u05d9 \u05e6\u05d3\u05e7 \u05e7\u05e8\u05d1\u05ea \u05d0\u05dc\u05d4\u05d9\u05dd \u05d9\u05d7\u05e4\u05e6\u05d5\u05df\u05c3\r\n"}}, {"book": "Isaiah", "chapter": 59, "verse": 4, "word": {"hebrewmodern": "\u05d0\u05d9\u05df \u05e7\u05e8\u05d0 \u05d1\u05e6\u05d3\u05e7 \u05d5\u05d0\u05d9\u05df \u05e0\u05e9\u05e4\u05d8 \u05d1\u05d0\u05de\u05d5\u05e0\u05d4 \u05d1\u05d8\u05d5\u05d7 \u05e2\u05dc \u05ea\u05d4\u05d5 \u05d5\u05d3\u05d1\u05e8 \u05e9\u05d5\u05d0 \u05d4\u05e8\u05d5 \u05e2\u05de\u05dc \u05d5\u05d4\u05d5\u05dc\u05d9\u05d3 \u05d0\u05d5\u05df\u05c3\r\n"}}, {"book": "Isaiah", "chapter": 59, "verse": 9, "word": {"hebrewmodern": "\u05e2\u05dc \u05db\u05df \u05e8\u05d7\u05e7 \u05de\u05e9\u05e4\u05d8 \u05de\u05de\u05e0\u05d5 \u05d5\u05dc\u05d0 \u05ea\u05e9\u05d9\u05d2\u05e0\u05d5 \u05e6\u05d3\u05e7\u05d4 \u05e0\u05e7\u05d5\u05d4 \u05dc\u05d0\u05d5\u05e8 \u05d5\u05d4\u05e0\u05d4 \u05d7\u05e9\u05da \u05dc\u05e0\u05d2\u05d4\u05d5\u05ea \u05d1\u05d0\u05e4\u05dc\u05d5\u05ea \u05e0\u05d4\u05dc\u05da\u05c3\r\n"}}, {"book": "Isaiah", "chapter": 59, "verse": 14, "word": {"hebrewmodern": "\u05d5\u05d4\u05e1\u05d2 \u05d0\u05d7\u05d5\u05e8 \u05de\u05e9\u05e4\u05d8 \u05d5\u05e6\u05d3\u05e7\u05d4 \u05de\u05e8\u05d7\u05d5\u05e7 \u05ea\u05e2\u05de\u05d3 \u05db\u05d9 \u05db\u05e9\u05dc\u05d4 \u05d1\u05e8\u05d7\u05d5\u05d1 \u05d0\u05de\u05ea \u05d5\u05e0\u05db\u05d7\u05d4 \u05dc\u05d0 \u05ea\u05d5\u05db\u05dc \u05dc\u05d1\u05d5\u05d0\u05c3\r\n"}}, {"book": "Jeremiah", "chapter": 22, "verse": 15, "word": {"hebrewmodern": "\u05d4\u05ea\u05de\u05dc\u05da \u05db\u05d9 \u05d0\u05ea\u05d4 \u05de\u05ea\u05d7\u05e8\u05d4 \u05d1\u05d0\u05e8\u05d6 \u05d0\u05d1\u05d9\u05da \u05d4\u05dc\u05d5\u05d0 \u05d0\u05db\u05dc \u05d5\u05e9\u05ea\u05d4 \u05d5\u05e2\u05e9\u05d4 \u05de\u05e9\u05e4\u05d8 \u05d5\u05e6\u05d3\u05e7\u05d4 \u05d0\u05d6 \u05d8\u05d5\u05d1 \u05dc\u05d5\u05c3\r\n"}}, {"book": "Jeremiah", "chapter": 23, "verse": 5, "word": {"hebrewmodern": "\u05d4\u05e0\u05d4 \u05d9\u05de\u05d9\u05dd \u05d1\u05d0\u05d9\u05dd \u05e0\u05d0\u05dd \u05d9\u05d4\u05d5\u05d4 \u05d5\u05d4\u05e7\u05de\u05ea\u05d9 \u05dc\u05d3\u05d5\u05d3 \u05e6\u05de\u05d7 \u05e6\u05d3\u05d9\u05e7 \u05d5\u05de\u05dc\u05da \u05de\u05dc\u05da \u05d5\u05d4\u05e9\u05db\u05d9\u05dc \u05d5\u05e2\u05e9\u05d4 \u05de\u05e9\u05e4\u05d8 \u05d5\u05e6\u05d3\u05e7\u05d4 \u05d1\u05d0\u05e8\u05e5\u05c3\r\n"}}, {"book": "Jeremiah", "chapter": 31, "verse": 23, "word": {"hebrewmodern": "\u05db\u05d4 \u05d0\u05de\u05e8 \u05d9\u05d4\u05d5\u05d4 \u05e6\u05d1\u05d0\u05d5\u05ea \u05d0\u05dc\u05d4\u05d9 \u05d9\u05e9\u05e8\u05d0\u05dc \u05e2\u05d5\u05d3 \u05d9\u05d0\u05de\u05e8\u05d5 \u05d0\u05ea \u05d4\u05d3\u05d1\u05e8 \u05d4\u05d6\u05d4 \u05d1\u05d0\u05e8\u05e5 \u05d9\u05d4\u05d5\u05d3\u05d4 \u05d5\u05d1\u05e2\u05e8\u05d9\u05d5 \u05d1\u05e9\u05d5\u05d1\u05d9 \u05d0\u05ea \u05e9\u05d1\u05d5\u05ea\u05dd \u05d9\u05d1\u05e8\u05db\u05da \u05d9\u05d4\u05d5\u05d4 \u05e0\u05d5\u05d4 \u05e6\u05d3\u05e7 \u05d4\u05e8 \u05d4\u05e7\u05d3\u05e9\u05c3\r\n"}}, {"book": "Jeremiah", "chapter": 50, "verse": 7, "word": {"hebrewmodern": "\u05db\u05dc \u05de\u05d5\u05e6\u05d0\u05d9\u05d4\u05dd \u05d0\u05db\u05dc\u05d5\u05dd \u05d5\u05e6\u05e8\u05d9\u05d4\u05dd \u05d0\u05de\u05e8\u05d5 \u05dc\u05d0 \u05e0\u05d0\u05e9\u05dd \u05ea\u05d7\u05ea \u05d0\u05e9\u05e8 \u05d7\u05d8\u05d0\u05d5 \u05dc\u05d9\u05d4\u05d5\u05d4 \u05e0\u05d5\u05d4 \u05e6\u05d3\u05e7 \u05d5\u05de\u05e7\u05d5\u05d4 \u05d0\u05d1\u05d5\u05ea\u05d9\u05d4\u05dd \u05d9\u05d4\u05d5\u05d4\u05c3\r\n"}}, {"book": "Ezekiel", "chapter": 45, "verse": 9, "word": {"hebrewmodern": "\u05db\u05d4 \u05d0\u05de\u05e8 \u05d0\u05d3\u05e0\u05d9 \u05d9\u05d4\u05d5\u05d4 \u05e8\u05d1 \u05dc\u05db\u05dd \u05e0\u05e9\u05d9\u05d0\u05d9 \u05d9\u05e9\u05e8\u05d0\u05dc \u05d7\u05de\u05e1 \u05d5\u05e9\u05d3 \u05d4\u05e1\u05d9\u05e8\u05d5 \u05d5\u05de\u05e9\u05e4\u05d8 \u05d5\u05e6\u05d3\u05e7\u05d4 \u05e2\u05e9\u05d5 \u05d4\u05e8\u05d9\u05de\u05d5 \u05d2\u05e8\u05e9\u05ea\u05d9\u05db\u05dd \u05de\u05e2\u05dc \u05e2\u05de\u05d9 \u05e0\u05d0\u05dd \u05d0\u05d3\u05e0\u05d9 \u05d9\u05d4\u05d5\u05d4\u05c3\r\n"}}]}}}